PipUpdater/PipUpdater.py
PipUpdater/__init__.py
PipUpdater-0.0.1.dist-info/LICENSE
PipUpdater-0.0.1.dist-info/METADATA
PipUpdater-0.0.1.dist-info/WHEEL
PipUpdater-0.0.1.dist-info/top_level.txt
PipUpdater-0.0.1.dist-info/RECORD
