Metadata-Version: 2.1
Name: PipUpdater
Version: 0.0.1
Summary: This is a python package being developed for PyPi, that will be able to upgrade all of your packages.
Home-page: https://github.com/Crazypersonalph/PipUpdater
Author: Help Me Pls.
Author-email: 93847055+Crazypersonalph@users.noreply.github.com
License: UNKNOWN
Project-URL: Bug Tracker, https://github.com/Crazypersonalph/PipUpdater/issues
Platform: UNKNOWN
Classifier: Programming Language :: Python :: 3
Classifier: License :: Public Domain
Classifier: Operating System :: OS Independent
Requires-Python: >=3.0
License-File: LICENSE
